maoto_agent/__init__.py
maoto_agent/__main__.py
maoto_agent/app_types.py
maoto_agent/maoto_agent.py
maoto_agent-1.0.9.dist-info/LICENSE
maoto_agent-1.0.9.dist-info/METADATA
maoto_agent-1.0.9.dist-info/WHEEL
maoto_agent-1.0.9.dist-info/entry_points.txt
maoto_agent-1.0.9.dist-info/top_level.txt
maoto_agent-1.0.9.dist-info/RECORD
