Metadata-Version: 2.1
Name: maoto-agent
Version: 1.0.9
Summary: Maoto Agent
Author: Maoto
License: # Attribution-NonCommercial-NoDerivatives 4.0 International
Keywords: Maoto,Agent
Classifier: Programming Language :: Python :: 3
Classifier: Operating System :: OS Independent
Requires-Python: >=3.10
License-File: LICENSE
Requires-Dist: aiohttp>=3.8.6
Requires-Dist: aiofiles>=22.1.0
Requires-Dist: requests>=2.32.3
Requires-Dist: gql>=3.4.0
Requires-Dist: websockets>=10.4
Requires-Dist: numpy>=1.26.4
Requires-Dist: setuptools>=74.1.1
Requires-Dist: psutil>=6.0.0
Requires-Dist: starlette>=0.37.2
Requires-Dist: python-dateutil>=2.9.0
Requires-Dist: psycopg2-binary>=2.9.9
Requires-Dist: uvicorn[standard]>=0.30.1
Requires-Dist: ariadne>=0.23.0
Requires-Dist: gunicorn>=22.0.0
